LICENSE
README.md
pyproject.toml
schema_viewer/__about__.py
schema_viewer/__init__.py
schema_viewer/apps.py
schema_viewer/schema.py
schema_viewer/urls.py
schema_viewer/views.py
schema_viewer/static/schema-viewer/css/main.5636232d.css
schema_viewer/static/schema-viewer/js/main.58eb5a4ef.js
schema_viewer/templates/schema_viewer/index.html
schema_viewer/tests/__init__.py
schema_viewer/tests/test_schema.py
schema_viewer/tests/test_view.py
django_schema_viewer-0.5.3.dist-info/METADATA
django_schema_viewer-0.5.3.dist-info/WHEEL
django_schema_viewer-0.5.3.dist-info/licenses/LICENSE
django_schema_viewer-0.5.3.dist-info/RECORD
