Metadata-Version: 2.4
Name: django-schema-viewer
Version: 0.5.3
Summary: Visualizes a DB schema based on Django models
Project-URL: Documentation, https://github.com/pikhovkin/django-schema-viewer#readme
Project-URL: Issues, https://github.com/pikhovkin/django-schema-viewer/issues
Project-URL: Source, https://github.com/pikhovkin/django-schema-viewer
Author-email: Sergei Pikhovkin <s@pikhovkin.ru>
License-Expression: MIT
License-File: LICENSE
Keywords: database-gui,database-schema,django,django-models,django-schema,django-schema-graph,entity-relationship-diagram,er-diagram,erd,json-table-schema,schema,schema-diagram,schema-graph,schema-viewer,viewer
Classifier: Development Status :: 4 - Beta
Classifier: Environment :: Web Environment
Classifier: Framework :: Django :: 4.0
Classifier: Framework :: Django :: 4.1
Classifier: Framework :: Django :: 4.2
Classifier: Framework :: Django :: 5.0
Classifier: Framework :: Django :: 5.1
Classifier: License :: OSI Approved :: MIT License
Classifier: Operating System :: OS Independent
Classifier: Programming Language :: Python
Classifier: Programming Language :: Python :: 3
Classifier: Programming Language :: Python :: 3 :: Only
Classifier: Programming Language :: Python :: 3.10
Classifier: Programming Language :: Python :: 3.11
Classifier: Programming Language :: Python :: 3.12
Classifier: Programming Language :: Python :: 3.13
Classifier: Topic :: System :: Monitoring
Classifier: Topic :: Utilities
Requires-Python: >=3.10
Requires-Dist: django>=4.0
